uce/__init__.py
uce/eval_data.py
uce/eval_single_anndata.py
uce/evaluate.py
uce/model.py
uce/utils.py
uce/data_proc/__init__.py
uce/data_proc/data_utils.py
uce/data_proc/download_proc_czi_cxg.py
uce/data_proc/gene_embeddings.py
uce/data_proc/generate_reduced_chrom_files.py
uce/data_proc/preproc_many_dataset.py
uce_model-0.1.4.dist-info/LICENSE
uce_model-0.1.4.dist-info/METADATA
uce_model-0.1.4.dist-info/WHEEL
uce_model-0.1.4.dist-info/entry_points.txt
uce_model-0.1.4.dist-info/top_level.txt
uce_model-0.1.4.dist-info/RECORD
