Metadata-Version: 2.1
Name: uce-model
Version: 0.1.4
Summary: Universal Cell Embedding model for single-cell RNA-seq data
Author-email: Yanay Rosen <yanay@stanford.edu>
License: MIT License
Project-URL: Homepage, https://github.com/snap-stanford/UCE
Project-URL: Repository, https://github.com/snap-stanford/UCE.git
Keywords: single-cell,RNA-seq,embedding,pytorch,uce
Requires-Python: >=3.8
License-File: LICENSE
Requires-Dist: torch
Requires-Dist: numpy
Requires-Dist: scipy
Requires-Dist: pandas
Requires-Dist: tqdm
Requires-Dist: scanpy
Requires-Dist: accelerate
Requires-Dist: requests
Requires-Dist: urllib3
Requires-Dist: gdown
